ARIXA/Arixa_API.py
ARIXA/__init__.py
ARIXA-0.3.dist-info/LICENSE.txt
ARIXA-0.3.dist-info/METADATA
ARIXA-0.3.dist-info/WHEEL
ARIXA-0.3.dist-info/top_level.txt
ARIXA-0.3.dist-info/RECORD
