Metadata-Version: 2.1
Name: ARIXA
Version: 0.3
Summary: A Python library for controlling a robotic arm
Home-page: UNKNOWN
Author: Mohamed Ali
Author-email: arixa.robotics@gmail.com
License: UNKNOWN
Platform: UNKNOWN
Classifier: Programming Language :: Python :: 3
Classifier: License :: OSI Approved :: MIT License
License-File: LICENSE.txt
Requires-Dist: requests
